listenpy/__main__.py
listenpy/lib_hum.py
listenpy/lib_logic.py
listenpy/vosk-model-small-ru-0.22/README
listenpy/vosk-model-small-ru-0.22/am/final.mdl
listenpy/vosk-model-small-ru-0.22/conf/mfcc.conf
listenpy/vosk-model-small-ru-0.22/conf/model.conf
listenpy/vosk-model-small-ru-0.22/graph/Gr.fst
listenpy/vosk-model-small-ru-0.22/graph/HCLr.fst
listenpy/vosk-model-small-ru-0.22/graph/disambig_tid.int
listenpy/vosk-model-small-ru-0.22/graph/phones/word_boundary.int
listenpy/vosk-model-small-ru-0.22/ivector/final.dubm
listenpy/vosk-model-small-ru-0.22/ivector/final.ie
listenpy/vosk-model-small-ru-0.22/ivector/final.mat
listenpy/vosk-model-small-ru-0.22/ivector/global_cmvn.stats
listenpy/vosk-model-small-ru-0.22/ivector/online_cmvn.conf
listenpy/vosk-model-small-ru-0.22/ivector/splice.conf
listenpy-0.1.2.dist-info/METADATA
listenpy-0.1.2.dist-info/WHEEL
listenpy-0.1.2.dist-info/RECORD
