Metadata-Version: 2.1
Name: listenpy
Version: 0.1.2
Summary:  
Home-page: https://github.com/denisxab/listenpy
Author: Denis Kustov
Author-email: pro-progerkustov@yandex.ru
Requires-Python: >=3.10,<4.0
Classifier: Programming Language :: Python :: 3
Classifier: Programming Language :: Python :: 3.10
Classifier: Programming Language :: Python :: 3.11
Requires-Dist: pyaudio (>=0.2.13,<0.3.0)
Requires-Dist: requests (>=2.28.2,<3.0.0)
Requires-Dist: vosk (>=0.3.45,<0.4.0)
Project-URL: Repository, https://github.com/denisxab/listenpy
